pycotech/__init__.py
pycotech/loggers.py
pycotech/plw_player.py
pycotech/plw_recorder.py
pycotech/utils.py
pycotech/libs/usbpt104.dll
pycotech/libs/usbpt104.lib
pycotech-0.2.0.dist-info/COPYING
pycotech-0.2.0.dist-info/METADATA
pycotech-0.2.0.dist-info/WHEEL
pycotech-0.2.0.dist-info/entry_points.txt
pycotech-0.2.0.dist-info/top_level.txt
pycotech-0.2.0.dist-info/RECORD
