Metadata-Version: 2.1
Name: pycotech
Version: 0.2.0
Summary: Tools and wrappers to interface with PT-104 PicoLog® Data Loggers and files.
Home-page: https://gitlab.com/amv213/pycotech
Author: Alvise Vianello
Author-email: alvise@vianello.ai
License: UNKNOWN
Platform: UNKNOWN
Classifier: Development Status :: 4 - Beta
Classifier: Programming Language :: Python :: 3
Classifier: License :: OSI Approved :: GNU General Public License v3 or later (GPLv3+)
Classifier: Topic :: Scientific/Engineering
Classifier: Intended Audience :: End Users/Desktop
Classifier: Intended Audience :: Science/Research
Classifier: Operating System :: Microsoft :: Windows
Requires-Python: >=3.8
Requires-Dist: matplotlib
Requires-Dist: pandas
Requires-Dist: pyyaml
Requires-Dist: setuptools
Provides-Extra: doc
Requires-Dist: myst-parser ; extra == 'doc'
Requires-Dist: sphinx ; extra == 'doc'
Requires-Dist: sphinx-book-theme ; extra == 'doc'
Requires-Dist: sphinx-copybutton ; extra == 'doc'
Requires-Dist: sphinx-togglebutton ; extra == 'doc'
Requires-Dist: sphinx-panels ; extra == 'doc'
